.gitignore
README.md
setup.py
docs/Makefile
docs/conf.py
docs/index.rst
docs/make.bat
docs/_themes/LICENSE
docs/_themes/README.rst
docs/_themes/flask_theme_support.py
docs/_themes/kr/layout.html
docs/_themes/kr/relations.html
docs/_themes/kr/theme.conf
docs/_themes/kr/static/flasky.css_t
docs/_themes/kr/static/small_flask.css
docs/_themes/kr_small/layout.html
docs/_themes/kr_small/theme.conf
docs/_themes/kr_small/static/flasky.css_t
indicsyllabifier/__init__.py
indicsyllabifier/core.py
indicsyllabifier.egg-info/PKG-INFO
indicsyllabifier.egg-info/SOURCES.txt
indicsyllabifier.egg-info/dependency_links.txt
indicsyllabifier.egg-info/not-zip-safe
indicsyllabifier.egg-info/requires.txt
indicsyllabifier.egg-info/top_level.txt
indicsyllabifier/templates/indicsyllabifier.html
tests/__init__.py
tests/indcsyllabifier_test.py