Metadata-Version: 1.0
Name: indicsyllabifier
Version: 0.3
Summary: Syllabify each word in the given text
Home-page: http://silpa.org.in/Syllabize
Author: Santhosh Thottingal
Author-email: santhosh.thottingal@gmail.com
License: LGPL-3.0
Platform: UNKNOWN
